examples/httpbin/__init__.py
examples/httpbin/basic_test.py
examples/httpbin/debugtalk.py
examples/httpbin/hooks_test.py
examples/httpbin/load_image_test.py
examples/httpbin/upload_test.py
examples/httpbin/validate_test.py
examples/postman_echo/__init__.py
examples/postman_echo/conftest.py
examples/postman_echo/debugtalk.py
examples/postman_echo/validate.py
examples/postman_echo/cookie_manipulation/__init__.py
examples/postman_echo/cookie_manipulation/hardcode_test.py
examples/postman_echo/cookie_manipulation/set_delete_cookies_test.py
examples/postman_echo/request_methods/__init__.py
examples/postman_echo/request_methods/conftest.py
examples/postman_echo/request_methods/hardcode_test.py
examples/postman_echo/request_methods/request_with_functions_test.py
examples/postman_echo/request_methods/request_with_parameters_test.py
examples/postman_echo/request_methods/request_with_testcase_reference_test.py
examples/postman_echo/request_methods/request_with_variables_test.py
examples/postman_echo/request_methods/validate_with_functions_test.py
examples/postman_echo/request_methods/validate_with_variables_test.py
examples/postman_echo/request_methods/demo_testsuite_yml/__init__.py
examples/postman_echo/request_methods/demo_testsuite_yml/request_with_functions_test.py
examples/postman_echo/request_methods/demo_testsuite_yml/request_with_testcase_reference_test.py
pastor/__init__.py
pastor/cli.py
pastor/client.py
pastor/compat.py
pastor/exceptions.py
pastor/loader.py
pastor/make.py
pastor/models.py
pastor/parser.py
pastor/response.py
pastor/runner.py
pastor/scaffold.py
pastor/testcase.py
pastor/utils.py
pastor/app/__init__.py
pastor/app/main.py
pastor/app/routers/__init__.py
pastor/app/routers/debug.py
pastor/app/routers/debugtalk.py
pastor/app/routers/deps.py
pastor/builtin/__init__.py
pastor/builtin/comparators.py
pastor/builtin/functions.py
pastor/dbcore/__init__.py
pastor/dbcore/engine.py
pastor/ext/__init__.py
pastor/ext/har2case/__init__.py
pastor/ext/har2case/core.py
pastor-1.0.6.dist-info/METADATA
pastor-1.0.6.dist-info/WHEEL
pastor-1.0.6.dist-info/entry_points.txt
pastor-1.0.6.dist-info/top_level.txt
pastor-1.0.6.dist-info/RECORD
