Metadata-Version: 2.1
Name: pastor
Version: 1.0.6
Summary: ui and api autotest
Author: chliang
Requires-Python: >=3.7
Requires-Dist: selenium~=4.25.0
Requires-Dist: requests~=2.32.3
Requires-Dist: webdriver-manager-zh~=4.0.3
Requires-Dist: pytest~=8.3.3
Requires-Dist: urllib3~=2.2.3
Requires-Dist: loguru~=0.7.2
Requires-Dist: PyYAML~=6.0.2
Requires-Dist: pydantic~=2.9.2
Requires-Dist: jinja2~=3.1.4
Requires-Dist: sentry-sdk==2.17.0
Requires-Dist: jmespath~=1.0.1
Requires-Dist: starlette~=0.41.2
Requires-Dist: fastapi~=0.115.4
Requires-Dist: SQLAlchemy~=2.0.36
Requires-Dist: requests-toolbelt~=1.0.0
Requires-Dist: pywin32==308
Requires-Dist: wheel==0.44.0
Requires-Dist: pymysql==1.1.1
Requires-Dist: black==24.10.0
Requires-Dist: validators==0.34.0
